diss_ioc/__init__.py
diss_ioc/_version.py
diss_ioc/application.py
diss_ioc/bare.py
diss_ioc/controller.py
diss_ioc/device.py
diss_ioc/display.py
diss_ioc/event.py
diss_ioc/frame.py
diss_ioc/image.py
diss_ioc/ioc.py
diss_ioc/pvgroup.py
diss_ioc/viewer.py
diss_ioc/devices/base.py
diss_ioc/devices/eiger500k.py
diss_ioc/devices/sim.py
diss_ioc-0.1.4.dist-info/METADATA
diss_ioc-0.1.4.dist-info/WHEEL
diss_ioc-0.1.4.dist-info/entry_points.txt
diss_ioc-0.1.4.dist-info/top_level.txt
diss_ioc-0.1.4.dist-info/RECORD
