Metadata-Version: 2.4
Name: diss-ioc
Version: 0.1.4
Summary: CAproto-based pure-Python EPICS IOC for imaging detectors
Author-email: Matthias Rössle <matthias.roessle@helmholtz-berlin.de>, Florin Boariu <florin.pt@rootshell.ro>
License-Expression: GPL-3.0-or-later
Project-URL: Source, https://gitlab.com/kmc3-xpp/yadi-ioc
Project-URL: Issues, https://gitlab.com/kmc3-xpp/yadi-ioc/-/issues
Classifier: Programming Language :: Python :: 3
Classifier: Operating System :: POSIX :: Linux
Classifier: Development Status :: 2 - Pre-Alpha
Classifier: Environment :: Console
Classifier: Intended Audience :: Science/Research
Classifier: Topic :: Scientific/Engineering
Requires-Python: >=3.8
Requires-Dist: caproto
Requires-Dist: opentelemetry-api
Requires-Dist: opentelemetry-exporter-otlp
Requires-Dist: aiohttp
Requires-Dist: pyyaml
Requires-Dist: cbor2
Requires-Dist: numpy
Requires-Dist: dectris-compression
Requires-Dist: zmq
Provides-Extra: test
Requires-Dist: pytest; extra == "test"
Requires-Dist: pytest-cov; extra == "test"
Requires-Dist: pytest-asyncio; extra == "test"
Provides-Extra: display
Requires-Dist: matplotlib; extra == "display"
Provides-Extra: all
Requires-Dist: diss-ioc[display,test]; extra == "all"
